README
setup.py
jacknote/__init__.py
jacknote.egg-info/PKG-INFO
jacknote.egg-info/SOURCES.txt
jacknote.egg-info/dependency_links.txt
jacknote.egg-info/top_level.txt