Metadata-Version: 1.0
Name: jacknote
Version: 0.1.1
Summary: Jacknote
Home-page: https://radioframenetworks.com.com/kacknote
Author: jdev
Author-email: jdev@radioframenetworks.com
License: UNKNOWN
Platform: UNKNOWN
